meme_generator-0.2.2.dist-info/METADATA
meme_generator-0.2.2.dist-info/WHEEL
meme_generator.libs/libfontconfig-b548d5fd.so.1
meme_generator.libs/libfreetype-69d47f35.so.6
meme_generator.libs/libpng16-11497962.so.16
meme_generator.libs/libuuid-950e27f8.so.1
meme_generator/__init__.py
meme_generator/__init__.pyi
meme_generator/meme_generator.abi3.so
meme_generator/py.typed
meme_generator/resources/__init__.py
meme_generator/resources/__init__.pyi
meme_generator/tools/__init__.py
meme_generator/tools/__init__.pyi
meme_generator/tools/image_operations/__init__.py
meme_generator/tools/image_operations/__init__.pyi
meme_generator-0.2.2.dist-info/RECORD
